snappychain/__init__.py
snappychain/bm25sj.py
snappychain/chain.py
snappychain/chat.py
snappychain/devmode.py
snappychain/embedding.py
snappychain/epistemize.py
snappychain/graph.py
snappychain/loader.py
snappychain/output.py
snappychain/print.py
snappychain/prompt.py
snappychain/rag.py
snappychain/registry.py
snappychain/rerank.py
snappychain/schema.py
snappychain/splitter.py
snappychain/vectorstore.py
snappychain/wikipedia.py
snappychain-0.1.0.dist-info/LICENSE
snappychain-0.1.0.dist-info/METADATA
snappychain-0.1.0.dist-info/WHEEL
snappychain-0.1.0.dist-info/top_level.txt
snappychain-0.1.0.dist-info/RECORD
