Metadata-Version: 2.2
Name: snappychain
Version: 0.1.0
Summary: Add your description here
Requires-Python: >=3.11
License-File: LICENSE
Requires-Dist: bm25s-j>=0.1.1
Requires-Dist: chromadb>=0.6.3
Requires-Dist: langchain>=0.3.19
Requires-Dist: langchain-anthropic>=0.3.7
Requires-Dist: langchain-cohere>=0.4.2
Requires-Dist: langchain-community>=0.3.18
Requires-Dist: langchain-gemini>=0.1.1
Requires-Dist: langchain-ollama>=0.2.3
Requires-Dist: langchain-openai>=0.3.6
Requires-Dist: markitdown>=0.0.1a4
Requires-Dist: onelogger>=0.1.2
Requires-Dist: py2neo>=2021.2.4
Requires-Dist: pypdf>=5.3.0
